setup.py
orbit/__init__.py
orbit/satellite.py
orbit/tle.py
orbit/utilities.py
orbit.egg-info/PKG-INFO
orbit.egg-info/SOURCES.txt
orbit.egg-info/dependency_links.txt
orbit.egg-info/not-zip-safe
orbit.egg-info/top_level.txt