Metadata-Version: 1.0
Name: orbit
Version: 0.1
Summary: Gives current information about orbital objects of interest
Home-page: http://github.com/seanherron/orbit
Author: Sean Herron
Author-email: seanherron@gmail.com
License: MIT
Platform: UNKNOWN
